[{"id":1,"title":"Primer Producto","description":"Descripción Primer Producto","price":5000,"thumbnail":"Link Primer Producto","code":"A01","stock":1000},{"id":2,"title":"Segundo Producto","description":"Descripción Segundo Producto","price":5000,"thumbnail":"Link Segundo Producto","code":"A02","stock":1000},{"id":3,"title":"Tercer Producto","description":"Descripción Tercer Producto","price":5000,"thumbnail":"Link Tercer Producto","code":"A03","stock":1000},{"id":4,"title":"Cuarto Producto","description":"Descripción Cuarto Producto","price":5000,"thumbnail":"Link Cuarto Producto","code":"A04","stock":1000},{"id":5,"title":"Quinto Producto","description":"Descripción Quinto Producto","price":5000,"thumbnail":"Link Quinto Producto","code":"A05","stock":1000},{"id":6,"title":"Sexto Producto","description":"Descripción Sexto Producto","price":5000,"thumbnail":"Link Sexto Producto","code":"A06","stock":1000},{"id":7,"title":"Séptimo Producto","description":"Descripción Séptimo Producto","price":5000,"thumbnail":"Link Séptimo Producto","code":"A07","stock":1000},{"id":8,"title":"Octavo Producto","description":"Descripción Octavo Producto","price":5000,"thumbnail":"Link Octavo Producto","code":"A08","stock":1000},{"id":9,"title":"Noveno Producto","description":"Descripción Noveno Producto","price":5000,"thumbnail":"Link Noveno Producto","code":"A09","stock":1000},{"id":10,"title":"Décimo Producto","description":"Descripción Décimo Producto","price":5000,"thumbnail":"Link Décimo Producto","code":"A10","stock":1000}]